{
  "id": 7639,
  "cardNumber": "10026986",
  "name": "Worm King",
  "description": "This card can be Tribute Summoned in face-up Attack Position by Tributing 1 Reptile-Type \"Worm\" monster. You can Tribute 1 Reptile-Type \"Worm\" monster to select 1 card your opponent controls, and destroy it.",
  "cardLevel": 8,
  "cardRank": null,
  "atk": 2700,
  "def": 1100,
  "link": null,
  "subCategories": "[\"Effect\"]",
  "attribute": "Light",
  "linkArrows": [],
  "cardType": 1,
  "type": "[\"Reptile\"]"
}