{
  "id": 2469,
  "cardNumber": "50078509",
  "name": "Fiendish Chain",
  "description": "Activate this card by targeting 1 Effect Monster on the field; negate the effects of that face-up monster while it is on the field, also that face-up monster cannot attack. When it is destroyed, destroy this card.",
  "cardLevel": null,
  "cardRank": null,
  "atk": null,
  "def": null,
  "link": null,
  "subCategories": "[\"Continuous\"]",
  "attribute": null,
  "linkArrows": [],
  "cardType": 3,
  "type": "[]"
}