{
  "id": 6149,
  "cardNumber": "52551211",
  "name": "Shaddoll Hound",
  "description": "FLIP: You can target 1 \"Shaddoll\" card in your Graveyard; add it to your hand.<br>If this card is sent to the Graveyard by a card effect: You can target 1 monster on the field; change its battle position. (Flip monsters' effects are not activated at this time, except \"Shaddoll\" monsters'.) You can only use 1 \"Shaddoll Hound\" effect per turn, and only once that turn.",
  "cardLevel": 4,
  "cardRank": null,
  "atk": 1600,
  "def": 900,
  "link": null,
  "subCategories": "[\"Effect\",\"Flip\"]",
  "attribute": "Dark",
  "linkArrows": [],
  "cardType": 1,
  "type": "[\"Spellcaster\"]"
}