{
  "id": 889,
  "cardNumber": "73289035",
  "name": "Bujintei Tsukuyomi",
  "description": "2 Level 4 LIGHT monsters<br>Once per turn: You can detach 1 material from this card; send your entire hand to the GY (min. 1), and if you do, draw 2 cards. When this card you controlled while face-up leaves the field because of an opponent's card effect: You can target Level 4 Beast-Warrior \"Bujin\" monsters in your GY, up to the number of Xyz Materials this card had on the field; Special Summon those targets. You can only control 1 \"Bujintei Tsukuyomi\".",
  "cardLevel": null,
  "cardRank": 4,
  "atk": 1800,
  "def": 2300,
  "link": null,
  "subCategories": "[\"Effect\",\"Xyz\"]",
  "attribute": "Light",
  "linkArrows": [],
  "cardType": 1,
  "type": "[\"Beast-Warrior\"]"
}